quesadilla/__main__.py
quesadilla/cli/errors.py
quesadilla/cli/py.typed
quesadilla/cli/utils.py
quesadilla_cli-0.5.0.dist-info/LICENSE
quesadilla_cli-0.5.0.dist-info/METADATA
quesadilla_cli-0.5.0.dist-info/WHEEL
quesadilla_cli-0.5.0.dist-info/RECORD
