Metadata-Version: 2.1
Name: quesadilla-cli
Version: 0.5.0
Summary: An elegant background task queue for the more civilized age - command line interface
Home-page: https://gitlab.com/arcanery/python/quesadilla/quesadilla
License: GPL-3.0-or-later
Keywords: job,task,queue,async,actor
Author: Artur Ciesielski
Author-email: artur.ciesielski@gmail.com
Requires-Python: >=3.12,<4.0
Classifier: Development Status :: 3 - Alpha
Classifier: Intended Audience :: Developers
Classifier: Intended Audience :: System Administrators
Classifier: License :: OSI Approved :: GNU General Public License v3 or later (GPLv3+)
Classifier: Operating System :: OS Independent
Classifier: Programming Language :: Python :: 3
Classifier: Programming Language :: Python :: 3.12
Classifier: Programming Language :: Python :: 3.13
Classifier: Topic :: Software Development :: Libraries :: Application Frameworks
Classifier: Topic :: Software Development :: Libraries :: Python Modules
Classifier: Typing :: Typed
Requires-Dist: quesadilla-core (>=0.5.0,<0.6.0)
Requires-Dist: typer (>=0.12.5,<0.13.0)
Project-URL: Documentation, https://arcanery.gitlab.io/python/quesadilla/quesadilla/
Project-URL: Repository, https://gitlab.com/arcanery/python/quesadilla/cli
